pypeform/__init__.py
pypeform/hash.py
pypeform/models.py
pypeform/structure.py
pypeform-0.0.42.dist-info/LICENSE
pypeform-0.0.42.dist-info/WHEEL
pypeform-0.0.42.dist-info/METADATA
pypeform-0.0.42.dist-info/RECORD
